djcelery_email/__about__.py
djcelery_email/__init__.py
djcelery_email/backends.py
djcelery_email/conf.py
djcelery_email/models.py
djcelery_email/tasks.py
djcelery_email/utils.py
panevo_django_celery_email-4.0.0.dist-info/LICENSE
panevo_django_celery_email-4.0.0.dist-info/METADATA
panevo_django_celery_email-4.0.0.dist-info/WHEEL
panevo_django_celery_email-4.0.0.dist-info/top_level.txt
panevo_django_celery_email-4.0.0.dist-info/RECORD
